odoo/addons/l10n_de_tax_statement_zm/README.rst
odoo/addons/l10n_de_tax_statement_zm/__init__.py
odoo/addons/l10n_de_tax_statement_zm/__manifest__.py
odoo/addons/l10n_de_tax_statement_zm/i18n/de.po
odoo/addons/l10n_de_tax_statement_zm/i18n/l10n_de_tax_statement_zm.pot
odoo/addons/l10n_de_tax_statement_zm/models/__init__.py
odoo/addons/l10n_de_tax_statement_zm/models/l10n_de_tax_statement.py
odoo/addons/l10n_de_tax_statement_zm/models/l10n_de_tax_statement_zm_line.py
odoo/addons/l10n_de_tax_statement_zm/readme/CONFIGURE.md
odoo/addons/l10n_de_tax_statement_zm/readme/CONTRIBUTORS.md
odoo/addons/l10n_de_tax_statement_zm/readme/DESCRIPTION.md
odoo/addons/l10n_de_tax_statement_zm/readme/INSTALL.md
odoo/addons/l10n_de_tax_statement_zm/readme/ROADMAP.md
odoo/addons/l10n_de_tax_statement_zm/readme/USAGE.md
odoo/addons/l10n_de_tax_statement_zm/report/report_tax_statement.xml
odoo/addons/l10n_de_tax_statement_zm/security/ir.model.access.csv
odoo/addons/l10n_de_tax_statement_zm/static/description/icon.png
odoo/addons/l10n_de_tax_statement_zm/static/description/index.html
odoo/addons/l10n_de_tax_statement_zm/tests/__init__.py
odoo/addons/l10n_de_tax_statement_zm/tests/test_l10n_de_tax_statement_zm.py
odoo/addons/l10n_de_tax_statement_zm/views/l10n_de_vat_statement_view.xml
odoo/addons/l10n_de_tax_statement_zm/views/report_tax_statement.xml
odoo_addon_l10n_de_tax_statement_zm-17.0.1.0.1.dist-info/METADATA
odoo_addon_l10n_de_tax_statement_zm-17.0.1.0.1.dist-info/WHEEL
odoo_addon_l10n_de_tax_statement_zm-17.0.1.0.1.dist-info/top_level.txt
odoo_addon_l10n_de_tax_statement_zm-17.0.1.0.1.dist-info/RECORD
