Metadata-Version: 2.1
Name: odoo-addon-l10n_de_tax_statement_zm
Version: 17.0.1.0.1
Requires-Python: >=3.10
Requires-Dist: odoo-addon-l10n_de_tax_statement>=17.0dev,<17.1dev
Requires-Dist: odoo>=17.0a,<17.1dev
Summary: German VAT Statement Extension
Home-page: https://github.com/OCA/l10n-germany
License: AGPL-3
Author: OpenBIG.org, Onestein, sewisoft, Odoo Community Association (OCA)
Author-email: support@odoo-community.org
Classifier: Programming Language :: Python
Classifier: Framework :: Odoo
Classifier: Framework :: Odoo :: 17.0
Classifier: License :: OSI Approved :: GNU Affero General Public License v3
